OneFlow/__init__.py
OneFlow/utils/__init__.py
OneFlow/utils/callbacks.py
OneFlow/utils/common.py
OneFlow/utils/data_mgmt.py
OneFlow/utils/model.py
OneFlow_Hassi34-0.0.7.dist-info/LICENSE
OneFlow_Hassi34-0.0.7.dist-info/METADATA
OneFlow_Hassi34-0.0.7.dist-info/WHEEL
OneFlow_Hassi34-0.0.7.dist-info/top_level.txt
OneFlow_Hassi34-0.0.7.dist-info/RECORD
